ansaittua/__init__.py
ansaittua/__main__.py
ansaittua/ansaittua.py
ansaittua/cli.py
test/__init__.py
test/conftest.py
test/test_ansaittua.py
test/test_cli.py
ansaittua-2022.7.30.dist-info/LICENSE
ansaittua-2022.7.30.dist-info/METADATA
ansaittua-2022.7.30.dist-info/WHEEL
ansaittua-2022.7.30.dist-info/entry_points.txt
ansaittua-2022.7.30.dist-info/top_level.txt
ansaittua-2022.7.30.dist-info/RECORD
