Metadata-Version: 2.1
Name: ansaittua
Version: 2022.7.30
Summary: Earned Value Management (Finnish: ansaittua arvonhallintaa) when coding swiftly.
Home-page: https://git.sr.ht/~sthagen/ansaittua
Author: Stefan Hagen
Author-email: stefan@hagen.link
Maintainer: Stefan Hagen
Maintainer-email: stefan@hagen.link
Project-URL: Bug Tracker, https://todo.sr.ht/~sthagen/ansaittua
Project-URL: Documentation, https://codes.dilettant.life/docs/ansaittua
Project-URL: Source Code, https://git.sr.ht/~sthagen/ansaittua
Project-URL: Test Coverage, https://codes.dilettant.life/coverage/ansaittua
Keywords: code-generation,developer-tools,validation,verification
Classifier: Development Status :: 5 - Production/Stable
Classifier: Intended Audience :: Developers
Classifier: License :: OSI Approved :: MIT License
Classifier: Programming Language :: Python :: 3.10
Classifier: Programming Language :: Python :: 3.8
Classifier: Programming Language :: Python :: 3.9
Requires-Python: >=3.8
License-File: LICENSE
Requires-Dist: atlassian-python-api (>=3.25.0)
Requires-Dist: cogapp (>=3.3.0)
Requires-Dist: jmespath (>=1.0.1)
Requires-Dist: pydantic (>=1.9.1)
Requires-Dist: requests-cache (>=0.9.5)
Requires-Dist: scooby (>=0.6.0)
Requires-Dist: typer (>=0.6.1)
